Metadata-Version: 1.0
Name: my-flawless-lib
Version: 0.1.0
Summary: Names and length
Home-page: UNKNOWN
Author: Ewa Wandzilak
Author-email: ejstawiska@gmail.com
License: UNKNOWN
Platform: UNKNOWN
